<?xml version="1.0" encoding="UTF-8"?>
<!--
 ! (c) Copyright 2005-2012 JAXIO, www.jaxio.com
 ! Source code generated by Celerio, a Jaxio product
 ! Want to use Celerio within your company? email us at info@jaxio.com
 ! Follow us on twitter: @springfuse
 ! Template pack-jsf2-primefaces:src/main/webapp/WEB-INF/flows/edit/editFlow.e.vm.xml
-->
<flow xmlns="http://www.springframework.org/schema/webflow" xmlns:xsi="http://www.w3.org/2001/XMLSchema-instance"
	xsi:schemaLocation="http://www.springframework.org/schema/webflow http://www.springframework.org/schema/webflow/spring-webflow-2.0.xsd"
	parent="abstract/edit">
	
	<!-- note: this flow inherits from the abstract/edit flow -->

	<persistence-context />

	<!-- Flow input parameters -->
	<!-- tdTagRelation: the entity to edit. If null, then we create it here -->
	<input name="tdTagRelation" required="false" value="flowScope.tdTagRelation"/>	
	<on-start>
		<evaluate expression="tdTagRelationController.newIfNull(tdTagRelation)" result="flowScope.tdTagRelation" />
	</on-start>

	<decision-state id="startChoice">
		<if test="sub" then="tdTagRelationSubEdit" else="tdTagRelationEdit" />
	</decision-state>

	<!-- EDIT -->
	<view-state id="tdTagRelationEdit" parent="#tdTagRelationEditCommon">
		<on-render>
			<evaluate expression="flowsMenuHandler.updateMenu(flowRequestContext,tdTagRelation.id,tdTagRelationConverter.print(tdTagRelation))" />
		</on-render>

		<transition on="send">
			<evaluate expression="messageUtil.info('status_submitted_ok')" />
		</transition>

		<transition on="save">
			<evaluate expression="tdTagRelationController.save(tdTagRelation)" />
		</transition>

		<transition on="saveAndClose">
			<evaluate expression="tdTagRelationController.saveAndClose(tdTagRelation)" />
		</transition>

		<transition on="close">
			<evaluate expression="primeFacesUtil.showAskForSaveDialog(persistenceContext,tdTagRelation)"/>
		</transition>

		<transition on="deleteAndClose" to="deleteAndClose">
			<evaluate expression="tdTagRelationController.delete(tdTagRelation)" />
		</transition>
	</view-state>

	<!-- SUB-EDIT -->
	<view-state id="tdTagRelationSubEdit" view="tdTagRelationEdit.xhtml" parent="#tdTagRelationEditCommon">
		<transition on="ok">
			<evaluate expression="primeFacesUtil.forceClose()" />
		</transition>
		<transition on="cancel" to="cancelEdit" />
	</view-state>

	<!-- COMMON-EDIT -->
	<view-state id="tdTagRelationEditCommon">

		<!-- parentTag transitions (x-to-one) -->
		<transition on="selectParentTag" to="selectParentTag" />
		<transition on="editParentTag" to="editParentTag">
			<set name="requestScope.paramReadonly" value="false" type="boolean" />
		</transition>
		<transition on="viewParentTag" to="editParentTag">
			<set name="requestScope.paramReadonly" value="true" type="boolean" />
		</transition>

		<!-- currentTag transitions (x-to-one) -->
		<transition on="selectCurrentTag" to="selectCurrentTag" />
		<transition on="editCurrentTag" to="editCurrentTag">
			<set name="requestScope.paramReadonly" value="false" type="boolean" />
		</transition>
		<transition on="viewCurrentTag" to="editCurrentTag">
			<set name="requestScope.paramReadonly" value="true" type="boolean" />
		</transition>
	</view-state>

	<!-- SUBFLOW parentTag (x-to-one) -->
	<subflow-state id="selectParentTag" subflow="tdTag">
		<input name="sub" value="true" />
		<transition on="tdTagSelected" to="startChoice">
			<evaluate expression="tdTagRelation.setParentTag(currentEvent.attributes.tdTagSelected)" />
			<evaluate expression="messageUtil.info('status_selected_ok',resourceBundle.tdTagRelation_parentTag)" />
		</transition>
		<transition on="cancel" to="startChoice" />
	</subflow-state>
	<subflow-state id="editParentTag" subflow="tdTag/edit">
		<input name="sub" value="true" />
		<input name="readonly" value="requestScope.paramReadonly" />
		<input name="tdTag" value="tdTagRelation.parentTag" />
		<transition on="endEdit" to="startChoice">
			<evaluate expression="messageUtil.info('status_edited_ok',resourceBundle.tdTagRelation_parentTag)" />
		</transition>
		<transition on="cancelEdit" to="startChoice" />
	</subflow-state>


	<!-- SUBFLOW currentTag (x-to-one) -->
	<subflow-state id="selectCurrentTag" subflow="tdTag">
		<input name="sub" value="true" />
		<transition on="tdTagSelected" to="startChoice">
			<evaluate expression="tdTagRelation.setCurrentTag(currentEvent.attributes.tdTagSelected)" />
			<evaluate expression="messageUtil.info('status_selected_ok',resourceBundle.tdTagRelation_currentTag)" />
		</transition>
		<transition on="cancel" to="startChoice" />
	</subflow-state>
	<subflow-state id="editCurrentTag" subflow="tdTag/edit">
		<input name="sub" value="true" />
		<input name="readonly" value="requestScope.paramReadonly" />
		<input name="tdTag" value="tdTagRelation.currentTag" />
		<transition on="endEdit" to="startChoice">
			<evaluate expression="messageUtil.info('status_edited_ok',resourceBundle.tdTagRelation_currentTag)" />
		</transition>
		<transition on="cancelEdit" to="startChoice" />
	</subflow-state>

	<end-state id="endEdit">
		<output name="tdTagRelation" value="tdTagRelation" />
	</end-state>
</flow>